python_readenv-0.7.1.dist-info/licenses/AUTHORS
python_readenv-0.7.1.dist-info/licenses/LICENSE
readenv/__init__.py
readenv/_environ.py
readenv/_version.py
readenv/loads.py
readenv/mypy.py
readenv/py.typed
python_readenv-0.7.1.dist-info/METADATA
python_readenv-0.7.1.dist-info/WHEEL
python_readenv-0.7.1.dist-info/top_level.txt
python_readenv-0.7.1.dist-info/RECORD
