Metadata-Version: 2.4
Name: python-readenv
Version: 0.7.1
Summary: read an env file and export to os.environ
Author-email: Raffaele Salmaso <raffaele.salmaso@gmail.com>
License-Expression: MIT
Project-URL: Home Page, https://pypi.org/project/python-readenv/
Project-URL: Documentation, https://github.com/rsalmaso/python-readenv/blob/main/README.md
Project-URL: GitHub, https://github.com/rsalmaso/python-readenv
Project-URL: Changelog, https://github.com/rsalmaso/python-readenv/blob/main/CHANGELOG.md
Project-URL: Bug Reports, https://github.com/rsalmaso/python-readenv/discussions
Keywords: env,envvar,environ,environment,environment variable
Classifier: Development Status :: 5 - Production/Stable
Classifier: Operating System :: OS Independent
Classifier: Environment :: Web Environment
Classifier: Programming Language :: Python
Classifier: Topic :: Software Development :: Libraries :: Python Modules
Classifier: Programming Language :: Python :: 3
Classifier: Programming Language :: Python :: 3.8
Classifier: Programming Language :: Python :: 3.9
Classifier: Programming Language :: Python :: 3.10
Classifier: Programming Language :: Python :: 3.11
Classifier: Programming Language :: Python :: 3.12
Classifier: Programming Language :: Python :: 3.13
Requires-Python: >=3.8
License-File: LICENSE
License-File: AUTHORS
Dynamic: license-file
